api_provider.py
main.py
parser.py
server.py
edhrec_mcp-1.0.4.dist-info/METADATA
edhrec_mcp-1.0.4.dist-info/WHEEL
edhrec_mcp-1.0.4.dist-info/entry_points.txt
edhrec_mcp-1.0.4.dist-info/top_level.txt
edhrec_mcp-1.0.4.dist-info/RECORD
